video_to_mp3/__init__.py
video_to_mp3/__main__.py
video_to_mp3/cli.py
video_to_mp3/video_to_mp3.py
video_to_mp3-0.2.dist-info/METADATA
video_to_mp3-0.2.dist-info/WHEEL
video_to_mp3-0.2.dist-info/entry_points.txt
video_to_mp3-0.2.dist-info/top_level.txt
video_to_mp3-0.2.dist-info/RECORD
